objspect/__init__.py
objspect/objspect.py
objspect-0.1.0.dist-info/licenses/LICENSE
objspect-0.1.0.dist-info/METADATA
objspect-0.1.0.dist-info/WHEEL
objspect-0.1.0.dist-info/top_level.txt
objspect-0.1.0.dist-info/RECORD
